pytrendseries/__init__.py
pytrendseries/detecttrend.py
pytrendseries/time_under_water.py
pytrendseries/version.py
pytrendseries/vizplot.py
pytrendseries-0.1.10.dist-info/METADATA
pytrendseries-0.1.10.dist-info/WHEEL
pytrendseries-0.1.10.dist-info/RECORD
