Metadata-Version: 2.3
Name: pytrendseries
Version: 0.1.10
Summary: Detect trend in timeseries.
License: MIT
Author: Rafael Rodrigues
Requires-Python: >=3.8,<4.0
Classifier: License :: OSI Approved :: MIT License
Classifier: Programming Language :: Python :: 3
Classifier: Programming Language :: Python :: 3.8
Classifier: Programming Language :: Python :: 3.9
Classifier: Programming Language :: Python :: 3.10
Classifier: Programming Language :: Python :: 3.11
Classifier: Programming Language :: Python :: 3.12
Classifier: Programming Language :: Python :: 3.13
Requires-Dist: matplotlib (<=3.7.1) ; python_full_version <= "3.9.0"
Requires-Dist: matplotlib (>=3.10.0) ; python_version >= "3.10"
Requires-Dist: pandas (<=1.5.3) ; python_full_version <= "3.9.0"
Requires-Dist: pandas (>=2.2.3) ; python_version >= "3.10"
Requires-Dist: tqdm (>=4.60.0,<5.0.0)
